jsonmodipy/Hardcoded.py
jsonmodipy/Mod_file.py
jsonmodipy/PythonSetter.py
jsonmodipy/PythonStructures.py
jsonmodipy/__init__.py
jsonmodipy/__main__.py
jsonmodipy/comparison.py
jsonmodipy/file_parsing.py
jsonmodipy/helper.py
jsonmodipy/apply/__init__.py
jsonmodipy/apply/clss.py
jsonmodipy/apply/file.py
jsonmodipy/apply/function.py
jsonmodipy/apply/function_helper.py
jsonmodipy/apply/inject_func_docstr.py
jsonmodipy/arg_parser/__init__.py
jsonmodipy/arg_parser/arg_values_checks.py
jsonmodipy/arg_parser/parse_args.py
jsonmodipy/arg_parser/process_args_apply.py
jsonmodipy/arg_parser/process_args_ask.py
jsonmodipy/arg_parser/process_args_engine.py
jsonmodipy/arg_parser/process_args_get.py
jsonmodipy/arg_parser/process_args_set.py
jsonmodipy/ask_llm/__init__.py
jsonmodipy/ask_llm/ask_gpt.py
jsonmodipy/ask_llm/clss.py
jsonmodipy/ask_llm/file.py
jsonmodipy/ask_llm/function.py
jsonmodipy/chatgpt35/__init__.py
jsonmodipy/chatgpt35/credentials.py
jsonmodipy/chatgpt35/helper.py
jsonmodipy/chatgpt35/login_chatgpt35.py
jsonmodipy/chatgpt35/website_question.py
jsonmodipy/chatgpt35/conversations/Conversation.py
jsonmodipy/chatgpt35/conversations/Gpt_message.py
jsonmodipy/chatgpt35/conversations/__init__.py
jsonmodipy/create_json/__init__.py
jsonmodipy/create_json/clss.py
jsonmodipy/create_json/file.py
jsonmodipy/create_json/function.py
jsonmodipy/get/__init__.py
jsonmodipy/get/argument_getting.py
jsonmodipy/get/clss.py
jsonmodipy/get/file.py
jsonmodipy/get/function.py
jsonmodipy/get/function_location.py
jsonmodipy/get/helper.py
jsonmodipy/get/helper_function.py
jsonmodipy/gpt_output/__init__.py
jsonmodipy/gpt_output/gpt_output_paths.py
jsonmodipy/gpt_output/output_to_func_docstr.py
jsonmodipy/gpt_output/store_output.py
jsonmodipy/gpt_output/verify_func_code.py
jsonmodipy/gpt_output/verify_func_docstr.py
jsonmodipy/gpt_output/ask_for_improvement/__init__.py
jsonmodipy/set/__init__.py
jsonmodipy/set/create_jsonstructure.py
jsonmodipy-0.0.8.dist-info/METADATA
jsonmodipy-0.0.8.dist-info/WHEEL
jsonmodipy-0.0.8.dist-info/entry_points.txt
jsonmodipy-0.0.8.dist-info/top_level.txt
jsonmodipy-0.0.8.dist-info/RECORD
